ak_safe/__init__.py
ak_safe/wrapper.py
ak_safe/Enumeration/Force.py
ak_safe/Enumeration/ItemType.py
ak_safe/Enumeration/Length.py
ak_safe/Enumeration/Temperature.py
ak_safe/Enumeration/Units.py
ak_safe/Enumeration/__init__.py
ak_safe/Model/model.py
ak_safe/utils/__init__.py
ak_safe/utils/credentials.py
ak_safe/utils/definitions.py
ak_safe/utils/logger.py
ak_safe-0.0.1.dist-info/entry_points.txt
ak_safe-0.0.1.dist-info/LICENSE
ak_safe-0.0.1.dist-info/WHEEL
ak_safe-0.0.1.dist-info/METADATA
ak_safe-0.0.1.dist-info/RECORD
