Metadata-Version: 2.1
Name: ak_safe
Version: 0.0.1
Summary: Python wrapper for SAFE API
Author-email: Arun Kishore <pypi@rpakishore.co.in>
Requires-Python: >=3.11.0
Classifier: License :: OSI Approved :: Mozilla Public License 2.0 (MPL 2.0)
Requires-Dist: comtypes==1.2.0
Requires-Dist: forallpeople==2.6.7
Requires-Dist: pandas==2.1.3
Requires-Dist: rich==13.7.0
Requires-Dist: typer[all]==0.9.0
Requires-Dist: ipykernel ; extra == "dev"
Requires-Dist: ipywidgets ; extra == "dev"
Requires-Dist: pandasgui ; extra == "dev"
Requires-Dist: line-profiler ; extra == "dev"
Requires-Dist: pytest==7.4.3 ; extra == "test"
Project-URL: Home, https://github.com/rpakishore/ak_safe
Provides-Extra: dev
Provides-Extra: test
